jdk/__init__.py
install_jdk_patch-0.2.1a0.dist-info/LICENSE.md
install_jdk_patch-0.2.1a0.dist-info/METADATA
install_jdk_patch-0.2.1a0.dist-info/WHEEL
install_jdk_patch-0.2.1a0.dist-info/top_level.txt
install_jdk_patch-0.2.1a0.dist-info/RECORD
