Metadata-Version: 2.1
Name: install-jdk-patch
Version: 0.2.1a0
Summary: Installs AdoptOpenJDK Java
Home-page: https://github.com/Robbie-Palmer/install-jdk
Keywords: AdoptOpenJDK Java jdk jre
Classifier: Development Status :: 5 - Production/Stable
Classifier: Intended Audience :: Developers
Classifier: Programming Language :: Python :: 3
Classifier: License :: OSI Approved :: MIT License
Classifier: Operating System :: OS Independent
Classifier: Topic :: Software Development
Classifier: Topic :: Utilities
Requires-Python: >=3.6
License-File: LICENSE.md
